mvip/.DS_Store
mvip/__init__.py
mvip/cli.py
mvip/data/.DS_Store
mvip/data/ICTV_Taxonomy_List.tsv
mvip/data/example_metadata.txt
mvip/data/miuvig_template-custom.txt
mvip/modules/03_anicalc.py
mvip/modules/03_aniclust.py
mvip/modules/MVP_00_set_up_MVP.py
mvip/modules/MVP_01_run_genomad_checkv.py
mvip/modules/MVP_02_filter_genomad_checkv.py
mvip/modules/MVP_03_do_clustering.py
mvip/modules/MVP_04_do_read_mapping.py
mvip/modules/MVP_05_create_vOTU_table.py
mvip/modules/MVP_06_do_functional_annotation.py
mvip/modules/MVP_07_do_binning.py
mvip/modules/MVP_100_summarize_outputs.py
mvip/modules/MVP_99_prep_MIUViG_submission.py
mvip/modules/__init__.py
mvip/modules/parse_annotation_result.sh
mvip-1.1.5.dist-info/entry_points.txt
mvip-1.1.5.dist-info/LICENSE
mvip-1.1.5.dist-info/WHEEL
mvip-1.1.5.dist-info/METADATA
mvip-1.1.5.dist-info/RECORD
