Metadata-Version: 2.1
Name: mvip
Version: 1.1.5
Summary: MVP: Modular Viromics Pipeline for studying viruses identified from sequencing data
Author-email: Clement Coclet <ccoclet@lbl.gov>
Classifier: License :: OSI Approved :: GNU General Public License v3 or later (GPLv3+)
Project-URL: Home, https://gitlab.com/ccoclet/mvp
